django_cupiddb/__init__.py
django_cupiddb/cache.py
django_cupiddb/utils.py
django_cupiddb-1.4.1.dist-info/LICENSE
django_cupiddb-1.4.1.dist-info/METADATA
django_cupiddb-1.4.1.dist-info/WHEEL
django_cupiddb-1.4.1.dist-info/top_level.txt
django_cupiddb-1.4.1.dist-info/RECORD
