Metadata-Version: 2.2
Name: django-cupiddb
Version: 1.4.1
Summary: CupidDB cache backend for Django
Author-email: Watt Iamsuri <wiamsuri@gmail.com>
License:                                  Apache License
Project-URL: Homepage, https://github.com/cupiddb/django-cupiddb
Keywords: cupiddb,cache,backend,django,in-memory database
Classifier: Framework :: Django
Classifier: Programming Language :: Python
Classifier: Programming Language :: Python :: 3 :: Only
Classifier: Programming Language :: Python :: 3.9
Classifier: Programming Language :: Python :: 3.10
Classifier: Programming Language :: Python :: 3.11
Classifier: Programming Language :: Python :: 3.12
Classifier: License :: OSI Approved :: Apache Software License
Classifier: Topic :: Utilities
Requires-Python: >=3.9
License-File: LICENSE
Requires-Dist: pycupiddb>=1.4.1
Requires-Dist: Django>=4.2
Provides-Extra: tests
Requires-Dist: pytest>=8.2.0; extra == "tests"
Requires-Dist: mypy>=1.10.0; extra == "tests"
Requires-Dist: pytest-cov>=5.0.0; extra == "tests"
